{
  "UnitID": 114,
  "HeroID": "blademaster_fire",
  "Family": "Blademaster",
  "Element": "Fire",
  "MinStar": 5,
  "MaxStar": 6,
  "Awakened": "false",
  "Universe": "Desert",
  "RecGear": [
    "Swift",
    "Blade",
    null
  ],
  "DefaultLevel": 1,
  "CanBeAwakened": true,
  "CharacterClass": "Assassin",
  "Strength": [
    {
      "tag": "BestInGame",
      "quality": 4
    },
    {
      "tag": "ArenaOffense",
      "quality": 3
    },
    {
      "tag": "Blitz",
      "quality": 2
    }
  ],
  "PowerUpXPTable": "NormalPowerUpXP",
  "AwakeningBonus": "Stat",
  "LeaderTraitStat": "AttackSpeed",
  "LeaderTraitCondition": "Any",
  "AwakeningEssenceIDs": [
    "MidFireEssence",
    "HighFireEssence",
    "MidGenericEssence",
    "HighGenericEssence"
  ],
  "AwakeningEssenceAmounts": [
    10,
    20,
    5,
    15
  ],
  "LeaderTraitPercentageBoost": 0.24,
  "Name": {
    "en": "Blademaster",
    "fr": "Fine lame",
    "de": "Klingenmeisterin",
    "es": "Maestra de la espada"
  },
  "Stats": [
    {
      "Star": 1,
      "Range": 3,
      "Accuracy": 0,
      "CritRate": 0.15,
      "MaxAttack": 186,
      "MoveSpeed": 5,
      "MaxHealth": 5822,
      "MinAttack": 124,
      "MinHealth": 3881,
      "MaxDefense": 186,
      "CritDamage": 0.5,
      "MinDefense": 124,
      "Resistance": 0.15,
      "AttackSpeed": 1.7,
      "MOBAVisionRange": 13,
      "SkillCooldownSpeed": 1
    },
    {
      "Star": 2,
      "Range": 3,
      "Accuracy": 0,
      "CritRate": 0.15,
      "MaxAttack": 223,
      "MoveSpeed": 5,
      "MaxHealth": 6986,
      "MinAttack": 135,
      "MinHealth": 4234,
      "MaxDefense": 223,
      "CritDamage": 0.5,
      "MinDefense": 135,
      "Resistance": 0.15,
      "AttackSpeed": 1.7,
      "MOBAVisionRange": 13,
      "SkillCooldownSpeed": 1
    },
    {
      "Star": 3,
      "Range": 3,
      "Accuracy": 0,
      "CritRate": 0.15,
      "MaxAttack": 267,
      "MoveSpeed": 5,
      "MaxHealth": 8383,
      "MinAttack": 148,
      "MinHealth": 4657,
      "MaxDefense": 267,
      "CritDamage": 0.5,
      "MinDefense": 148,
      "Resistance": 0.15,
      "AttackSpeed": 1.7,
      "MOBAVisionRange": 13,
      "SkillCooldownSpeed": 1
    },
    {
      "Star": 4,
      "Range": 3,
      "Accuracy": 0,
      "CritRate": 0.15,
      "MaxAttack": 363,
      "MoveSpeed": 5,
      "MaxHealth": 11401,
      "MinAttack": 214,
      "MinHealth": 6706,
      "MaxDefense": 363,
      "CritDamage": 0.5,
      "MinDefense": 214,
      "Resistance": 0.15,
      "AttackSpeed": 1.7,
      "MOBAVisionRange": 13,
      "SkillCooldownSpeed": 1
    },
    {
      "Star": 5,
      "Range": 3,
      "Accuracy": 0,
      "CritRate": 0.15,
      "MaxAttack": 494,
      "MoveSpeed": 5,
      "MaxHealth": 15506,
      "MinAttack": 291,
      "MinHealth": 9121,
      "MaxDefense": 494,
      "CritDamage": 0.5,
      "MinDefense": 291,
      "Resistance": 0.15,
      "AttackSpeed": 1.7,
      "MOBAVisionRange": 13,
      "SkillCooldownSpeed": 1
    },
    {
      "Star": 6,
      "Range": 3,
      "Accuracy": 0,
      "CritRate": 0.15,
      "MaxAttack": 672,
      "MoveSpeed": 5,
      "MaxHealth": 21088,
      "MinAttack": 395,
      "MinHealth": 12405,
      "MaxDefense": 672,
      "CritDamage": 0.5,
      "MinDefense": 395,
      "Resistance": 0.15,
      "AttackSpeed": 1.7,
      "MOBAVisionRange": 13,
      "SkillCooldownSpeed": 1
    }
  ]
}