{
  "UnitID": 316,
  "HeroID": "golem_nature",
  "Family": "Golem",
  "Element": "Nature",
  "MinStar": 3,
  "MaxStar": 6,
  "Awakened": "false",
  "Universe": "Desert",
  "RecGear": [
    "Energy",
    "Energy",
    "Focus"
  ],
  "DefaultLevel": 1,
  "CanBeAwakened": true,
  "CharacterClass": "Tank",
  "Strength": [
    {
      "tag": "Moba",
      "quality": 2
    },
    {
      "tag": "ArenaDefense",
      "quality": 1
    },
    {
      "tag": "Blitz",
      "quality": 1
    }
  ],
  "PowerUpXPTable": "NormalPowerUpXP",
  "AwakeningBonus": "LeaderTrait",
  "LeaderTraitStat": null,
  "LeaderTraitCondition": null,
  "AwakeningEssenceIDs": [
    "LowNatureEssence",
    "MidNatureEssence",
    "LowGenericEssence",
    "MidGenericEssence"
  ],
  "AwakeningEssenceAmounts": [
    10,
    15,
    5,
    10
  ],
  "LeaderTraitPercentageBoost": null,
  "Name": {
    "en": "Golem",
    "fr": "Golem",
    "de": "Golem",
    "es": "Gólem"
  },
  "Stats": [
    {
      "Star": 1,
      "Range": 3,
      "Accuracy": 0,
      "CritRate": 0.15,
      "MaxAttack": 123,
      "MoveSpeed": 5,
      "MaxHealth": 5911,
      "MinAttack": 82,
      "MinHealth": 3941,
      "MaxDefense": 155,
      "CritDamage": 0.5,
      "MinDefense": 103,
      "Resistance": 0.15,
      "AttackSpeed": 1.55,
      "MOBAVisionRange": 13,
      "SkillCooldownSpeed": 1
    },
    {
      "Star": 2,
      "Range": 3,
      "Accuracy": 0,
      "CritRate": 0.15,
      "MaxAttack": 147,
      "MoveSpeed": 5,
      "MaxHealth": 7093,
      "MinAttack": 89,
      "MinHealth": 4299,
      "MaxDefense": 186,
      "CritDamage": 0.5,
      "MinDefense": 113,
      "Resistance": 0.15,
      "AttackSpeed": 1.55,
      "MOBAVisionRange": 13,
      "SkillCooldownSpeed": 1
    },
    {
      "Star": 3,
      "Range": 3,
      "Accuracy": 0,
      "CritRate": 0.15,
      "MaxAttack": 176,
      "MoveSpeed": 5,
      "MaxHealth": 8512,
      "MinAttack": 98,
      "MinHealth": 4729,
      "MaxDefense": 223,
      "CritDamage": 0.5,
      "MinDefense": 124,
      "Resistance": 0.15,
      "AttackSpeed": 1.55,
      "MOBAVisionRange": 13,
      "SkillCooldownSpeed": 1
    },
    {
      "Star": 4,
      "Range": 3,
      "Accuracy": 0,
      "CritRate": 0.15,
      "MaxAttack": 240,
      "MoveSpeed": 5,
      "MaxHealth": 11576,
      "MinAttack": 141,
      "MinHealth": 6809,
      "MaxDefense": 303,
      "CritDamage": 0.5,
      "MinDefense": 178,
      "Resistance": 0.15,
      "AttackSpeed": 1.55,
      "MOBAVisionRange": 13,
      "SkillCooldownSpeed": 1
    },
    {
      "Star": 5,
      "Range": 3,
      "Accuracy": 0,
      "CritRate": 0.15,
      "MaxAttack": 327,
      "MoveSpeed": 5,
      "MaxHealth": 15743,
      "MinAttack": 192,
      "MinHealth": 9261,
      "MaxDefense": 412,
      "CritDamage": 0.5,
      "MinDefense": 242,
      "Resistance": 0.15,
      "AttackSpeed": 1.55,
      "MOBAVisionRange": 13,
      "SkillCooldownSpeed": 1
    },
    {
      "Star": 6,
      "Range": 3,
      "Accuracy": 0,
      "CritRate": 0.15,
      "MaxAttack": 445,
      "MoveSpeed": 5,
      "MaxHealth": 21411,
      "MinAttack": 262,
      "MinHealth": 12595,
      "MaxDefense": 560,
      "CritDamage": 0.5,
      "MinDefense": 329,
      "Resistance": 0.15,
      "AttackSpeed": 1.55,
      "MOBAVisionRange": 13,
      "SkillCooldownSpeed": 1
    }
  ]
}