{
  "UnitID": 346,
  "HeroID": "grublinslinger_nature",
  "Family": "Grublin Slinger",
  "Element": "Nature",
  "MinStar": 2,
  "MaxStar": 6,
  "Awakened": "false",
  "Universe": "WesternFantasyForest",
  "RecGear": [
    "Fatal",
    "Blade",
    null
  ],
  "DefaultLevel": 1,
  "CanBeAwakened": true,
  "CharacterClass": "Marksman",
  "Strength": [
    {
      "tag": "Great",
      "quality": 2
    },
    {
      "tag": "BullAll",
      "quality": 1
    },
    {
      "tag": "Early",
      "quality": 0
    }
  ],
  "PowerUpXPTable": "NormalPowerUpXP",
  "AwakeningBonus": "Stat",
  "LeaderTraitStat": null,
  "LeaderTraitCondition": null,
  "AwakeningEssenceIDs": [
    "LowNatureEssence",
    "MidNatureEssence",
    "LowGenericEssence",
    "MidGenericEssence"
  ],
  "AwakeningEssenceAmounts": [
    20,
    1,
    15,
    1
  ],
  "LeaderTraitPercentageBoost": null,
  "Name": {
    "en": "Grublin Slinger",
    "fr": "Frondeur grublin",
    "de": "Grublin-Schleuderer",
    "es": "Hondero grublin"
  },
  "Stats": [
    {
      "Star": 1,
      "Range": 7,
      "Accuracy": 0,
      "CritRate": 0.15,
      "MaxAttack": 180,
      "MoveSpeed": 5,
      "MaxHealth": 4365,
      "MinAttack": 120,
      "MinHealth": 2910,
      "MaxDefense": 98,
      "CritDamage": 0.5,
      "MinDefense": 65,
      "Resistance": 0.15,
      "AttackSpeed": 1.55,
      "MOBAVisionRange": 13,
      "SkillCooldownSpeed": 1
    },
    {
      "Star": 2,
      "Range": 7,
      "Accuracy": 0,
      "CritRate": 0.15,
      "MaxAttack": 216,
      "MoveSpeed": 5,
      "MaxHealth": 5238,
      "MinAttack": 131,
      "MinHealth": 3175,
      "MaxDefense": 118,
      "CritDamage": 0.5,
      "MinDefense": 72,
      "Resistance": 0.15,
      "AttackSpeed": 1.55,
      "MOBAVisionRange": 13,
      "SkillCooldownSpeed": 1
    },
    {
      "Star": 3,
      "Range": 7,
      "Accuracy": 0,
      "CritRate": 0.15,
      "MaxAttack": 259,
      "MoveSpeed": 5,
      "MaxHealth": 6285,
      "MinAttack": 144,
      "MinHealth": 3492,
      "MaxDefense": 142,
      "CritDamage": 0.5,
      "MinDefense": 79,
      "Resistance": 0.15,
      "AttackSpeed": 1.55,
      "MOBAVisionRange": 13,
      "SkillCooldownSpeed": 1
    },
    {
      "Star": 4,
      "Range": 7,
      "Accuracy": 0,
      "CritRate": 0.15,
      "MaxAttack": 352,
      "MoveSpeed": 5,
      "MaxHealth": 8547,
      "MinAttack": 207,
      "MinHealth": 5028,
      "MaxDefense": 193,
      "CritDamage": 0.5,
      "MinDefense": 114,
      "Resistance": 0.15,
      "AttackSpeed": 1.55,
      "MOBAVisionRange": 13,
      "SkillCooldownSpeed": 1
    },
    {
      "Star": 5,
      "Range": 7,
      "Accuracy": 0,
      "CritRate": 0.15,
      "MaxAttack": 479,
      "MoveSpeed": 5,
      "MaxHealth": 11624,
      "MinAttack": 282,
      "MinHealth": 6838,
      "MaxDefense": 262,
      "CritDamage": 0.5,
      "MinDefense": 154,
      "Resistance": 0.15,
      "AttackSpeed": 1.55,
      "MOBAVisionRange": 13,
      "SkillCooldownSpeed": 1
    },
    {
      "Star": 6,
      "Range": 7,
      "Accuracy": 0,
      "CritRate": 0.15,
      "MaxAttack": 652,
      "MoveSpeed": 5,
      "MaxHealth": 15808,
      "MinAttack": 384,
      "MinHealth": 9299,
      "MaxDefense": 356,
      "CritDamage": 0.5,
      "MinDefense": 209,
      "Resistance": 0.15,
      "AttackSpeed": 1.55,
      "MOBAVisionRange": 13,
      "SkillCooldownSpeed": 1
    }
  ]
}