{
  "UnitId": 509,
  "HeroId": "rollerderby_dark",
  "Name": {
    "en": "Derby Girl",
    "fr": "Derby Girl",
    "de": "Derby Girl",
    "es": "Patinadora"
  },
  "Family": "Roller Derby",
  "Element": "Dark",
  "Class": "Assassin",
  "MinStar": 3,
  "MaxStar": 6,
  "DefaultLevel": 1,
  "Universe": "CyberPunk",
  "Awakened": false,
  "CanBeAwakened": true,
  "AwakeningEssence": [
    {
      "id": "LowDarkEssence",
      "quantity": 10
    },
    {
      "id": "MidDarkEssence",
      "quantity": 15
    },
    {
      "id": "LowGenericEssence",
      "quantity": 5
    },
    {
      "id": "MidGenericEssence",
      "quantity": 10
    }
  ],
  "Strength": [
    {
      "tag": "Great",
      "quality": 2
    },
    {
      "tag": "Moba",
      "quality": 2
    },
    {
      "tag": "ArenaDefense",
      "quality": 0
    }
  ],
  "RecommendedGear": [
    "Fatal",
    "Energy"
  ],
  "Leader": null,
  "Stats": [
    {
      "Star": 1,
      "Health": {
        "Min": 3435,
        "Max": 5153,
        "Step": 190.88888888888889
      },
      "Attack": {
        "Min": 106,
        "Max": 159,
        "Step": 5.888888888888889
      },
      "Defense": {
        "Min": 94,
        "Max": 141,
        "Step": 5.222222222222222
      },
      "Range": 3,
      "Accuracy": 0,
      "CritRate": 0.15,
      "MoveSpeed": 5,
      "CritDamage": 0.5,
      "Resistance": 0.15,
      "AttackSpeed": 1.55,
      "MOBAVisionRange": 13,
      "SkillCooldownSpeed": 1
    },
    {
      "Star": 2,
      "Health": {
        "Min": 3748,
        "Max": 6184,
        "Step": 128.21052631578948
      },
      "Attack": {
        "Min": 116,
        "Max": 191,
        "Step": 3.9473684210526314
      },
      "Defense": {
        "Min": 102,
        "Max": 169,
        "Step": 3.526315789473684
      },
      "Range": 3,
      "Accuracy": 0,
      "CritRate": 0.15,
      "MoveSpeed": 5,
      "CritDamage": 0.5,
      "Resistance": 0.15,
      "AttackSpeed": 1.55,
      "MOBAVisionRange": 13,
      "SkillCooldownSpeed": 1
    },
    {
      "Star": 3,
      "Health": {
        "Min": 4123,
        "Max": 7421,
        "Step": 113.72413793103448
      },
      "Attack": {
        "Min": 127,
        "Max": 229,
        "Step": 3.5172413793103448
      },
      "Defense": {
        "Min": 113,
        "Max": 203,
        "Step": 3.103448275862069
      },
      "Range": 3,
      "Accuracy": 0,
      "CritRate": 0.15,
      "MoveSpeed": 5,
      "CritDamage": 0.5,
      "Resistance": 0.15,
      "AttackSpeed": 1.55,
      "MOBAVisionRange": 13,
      "SkillCooldownSpeed": 1
    },
    {
      "Star": 4,
      "Health": {
        "Min": 5936,
        "Max": 10092,
        "Step": 106.56410256410257
      },
      "Attack": {
        "Min": 184,
        "Max": 312,
        "Step": 3.282051282051282
      },
      "Defense": {
        "Min": 162,
        "Max": 276,
        "Step": 2.923076923076923
      },
      "Range": 3,
      "Accuracy": 0,
      "CritRate": 0.15,
      "MoveSpeed": 5,
      "CritDamage": 0.5,
      "Resistance": 0.15,
      "AttackSpeed": 1.55,
      "MOBAVisionRange": 13,
      "SkillCooldownSpeed": 1
    },
    {
      "Star": 5,
      "Health": {
        "Min": 8074,
        "Max": 13725,
        "Step": 115.3265306122449
      },
      "Attack": {
        "Min": 249,
        "Max": 424,
        "Step": 3.5714285714285716
      },
      "Defense": {
        "Min": 221,
        "Max": 376,
        "Step": 3.163265306122449
      },
      "Range": 3,
      "Accuracy": 0,
      "CritRate": 0.15,
      "MoveSpeed": 5,
      "CritDamage": 0.5,
      "Resistance": 0.15,
      "AttackSpeed": 1.55,
      "MOBAVisionRange": 13,
      "SkillCooldownSpeed": 1
    },
    {
      "Star": 6,
      "Health": {
        "Min": 10980,
        "Max": 18666,
        "Step": 130.27118644067798
      },
      "Attack": {
        "Min": 339,
        "Max": 576,
        "Step": 4.016949152542373
      },
      "Defense": {
        "Min": 301,
        "Max": 511,
        "Step": 3.559322033898305
      },
      "Range": 3,
      "Accuracy": 0,
      "CritRate": 0.15,
      "MoveSpeed": 5,
      "CritDamage": 0.5,
      "Resistance": 0.15,
      "AttackSpeed": 1.55,
      "MOBAVisionRange": 13,
      "SkillCooldownSpeed": 1
    }
  ],
  "Skills": {
    "FirstSkill": {
      "id": "rollerderby_breakaway",
      "name": {
        "en": "Breakaway",
        "fr": "Échappée",
        "de": "Ausreißer",
        "es": "Liberación"
      },
      "description": {
        "en": "Gains the <font color='{buff_blue}'>{icon.haste}&nbsp;HASTE</font> buff and <font color='{menu_highlight_white}'>Empowers</font> her baseball bat. When Empowered, her next BONK! skill deals additional damage and <font color='{debuff_red}'>{icon.stun}&nbsp;STUNS</font>.",
        "fr": "Gagne <font color='{buff_blue}'>{icon.haste}&nbsp;HÂTE</font> et <font color='{menu_highlight_white}'>renforce</font> sa batte de base-ball. Une fois renforcée, la prochaine utilisation de la compétence VLAN&nbsp;! inflige des dégâts supplémentaires et <font color='{debuff_red}'>{icon.stun}&nbsp;PARALYSIE</font>.",
        "de": "Erhält den <font color='{buff_blue}'>{icon.haste}&nbsp;EILE</font>-Bonus und <font color='{menu_highlight_white}'>verstärkt</font> ihren Baseballschläger. Wenn die Verstärkung aktiv ist, fügt ihre nächste DONK!-Fertigkeit zusätzlichen Schaden zu und <font color='{debuff_red}'>{icon.stun}&nbsp;BETÄUBT</font>.",
        "es": "Obtiene el efecto positivo <font color='{buff_blue}'>{icon.haste}&nbsp;RAPIDEZ</font> y <font color='{menu_highlight_white}'>potencia</font> su bate de béisbol para infligir daño adicional y <font color='{debuff_red}'>{icon.stun}&nbsp;ATURDIR</font> al objetivo con la próxima activación de ¡PUM!"
      }
    },
    "SecondSkill": {
      "id": "rollerderby_powerJam",
      "name": {
        "en": "Power Jam",
        "fr": "Surcharge de puissance",
        "de": "Stärkeblockade",
        "es": "Choque de Poder"
      },
      "description": {
        "en": "Dashes in a line, damaging enemies. In addition, she <font color='{buff_blue}'>{icon.raise_def}&nbsp;RAISES DEF</font> and <font color='{buff_blue}'>{icon.raise_atk}&nbsp;RAISES ATK</font>.<br>Can be recast up to {Skill.MultiCastCount} times in a row.",
        "fr": "Fonce droit devant elle pour infliger des dégâts aux ennemis situés sur la ligne d'effet. Gagne <font color='{buff_blue}'>{icon.raise_def}&nbsp;DÉF+</font> et <font color='{buff_blue}'>{icon.raise_atk}&nbsp;ATT+</font>.<br>Cette compétence peut être relancée {Skill.MultiCastCount} fois de suite.",
        "de": "Sprintet auf einer Linie entlang und fügt Feinden Schaden zu. Sie <font color='{buff_blue}'>{icon.raise_def}&nbsp;ERHÖHT VTG.</font> und <font color='{buff_blue}'>{icon.raise_atk}&nbsp;ERHÖHT ANG.</font><br>Kann bis zu {Skill.MultiCastCount} Mal hintereinander gezaubert werden.",
        "es": "Esprinta en línea recta dañando a los enemigos. Además, <font color='{buff_blue}'>{icon.raise_def}&nbsp;AUMENTA DEF</font> y <font color='{buff_blue}'>{icon.raise_atk}&nbsp;ATQ</font>.<br>Se puede activar de nuevo un máximo de {Skill.MultiCastCount} veces seguidas."
      }
    },
    "ThirdSkill": {
      "id": "rollerderby_grandSlam",
      "name": {
        "en": "Grand Slam",
        "fr": "Grand chelem",
        "de": "Grand Slam",
        "es": "Gran Golpe"
      },
      "description": {
        "en": "Swings her baseball bat, damaging enemies and knocking them away. When each enemy lands, deals additional damage and <font color='{debuff_red}'>{icon.stun}&nbsp;STUNS</font>.",
        "fr": "Agite sa batte de baseball pour frapper les ennemis à proximité, ce qui leur inflige des dégâts et les repousse. La chute leur cause des dégâts supplémentaires et <font color='{debuff_red}'>{icon.stun}&nbsp;PARALYSIE</font>.",
        "de": "Sie schwingt ihren Baseballschläger, fügt Feinden Schaden zu und schlägt sie weg. Fügt ihnen bei der Landung zusätzlichen Schaden zu und <font color='{debuff_red}'>{icon.stun}&nbsp;BETÄUBT</font> sie.",
        "es": "Ataca a los enemigos con su bate de béisbol y los lanza por los aires. Cuando caen, inflige daño adicional y <font color='{debuff_red}'>{icon.stun}&nbsp;ATURDE</font>."
      }
    },
    "AutoAttackSkill": {
      "id": "rollerderby_bonk",
      "name": {
        "en": "BONK!",
        "fr": "VLAN&nbsp;!",
        "de": "Donk!",
        "es": "¡PUM!"
      },
      "description": {
        "en": "Swings her baseball bat, attacking nearby enemies. Each attack lowers the cooldown of {FirstSkill.name}.",
        "fr": "Agite sa batte de baseball pour frapper les ennemis à proximité. Chaque attaque réduit le rechargement de {FirstSkill.name}.",
        "de": "Schwingt ihren Baseballschläger und greift Feinde in der Nähe an. Jeder Angriff verringert die Abklingzeit von {FirstSkill.name}.",
        "es": "Ataca a los enemigos cercanos con su bate de béisbol. Cada ataque reduce el tiempo de recuperación de {FirstSkill.name}."
      }
    }
  },
  "DebugHero": false,
  "CanBeAcquired": true
}